gempaterkini/__init__.py
liveearthquakeindonesia-0.4.dist-info/LICENSE
liveearthquakeindonesia-0.4.dist-info/METADATA
liveearthquakeindonesia-0.4.dist-info/WHEEL
liveearthquakeindonesia-0.4.dist-info/top_level.txt
liveearthquakeindonesia-0.4.dist-info/RECORD
