Metadata-Version: 2.1
Name: liveearthquakeindonesia
Version: 0.4
Summary: The package will get the latest earthquake from BMKG
Home-page: https://github.com/rizalmustofa31/Latest-Indonesia-Earhquake
Author: Rizal Mustofa
Author-email: rizalmustofa31@gmail.com
License: UNKNOWN
Project-URL: Website, https://github.com/rizalmustofa31
Platform: UNKNOWN
Classifier: Programming Language :: Python :: 3
Classifier: License :: OSI Approved :: GNU General Public License v3 (GPLv3)
Classifier: Operating System :: OS Independent
Classifier: Development Status :: 5 - Production/Stable
Requires-Python: >=3.6
License-File: LICENSE
